kollo/__init__.py
kollo/__main__.py
kollo/cli.py
kollo/kollo.py
kollo/kollo2.py
kollo-1.0.1.data/scripts/kollo
kollo-1.0.1.dist-info/LICENSE.txt
kollo-1.0.1.dist-info/METADATA
kollo-1.0.1.dist-info/WHEEL
kollo-1.0.1.dist-info/top_level.txt
kollo-1.0.1.dist-info/zip-safe
kollo-1.0.1.dist-info/RECORD
