Metadata-Version: 2.1
Name: kollo
Version: 1.0.1
Summary: Extract collocations from VERT data
Home-page: UNKNOWN
Author: Danny McDonald
Author-email: daniel.mcdonald@uzh.ch
License: MIT
Keywords: corpus,linguistics,corpora,collocation,vert
Platform: UNKNOWN
Requires-Dist: tqdm
